{
  "collection": [
    {
      "label": "T-shirt rood",
      "url": "https://github.com/SamClercky/forme-src/blob/master/tshirtRood.png?raw=true",
      "description": "Dit is een rood t-shirt gemaakt met verfijnde stof en een exclusieve witte mier op de borst.",
      "stars": 0,
      "stared": false,
      "highlighted": false,
      "price": 20
    },
    {
      "label": "T-shirt wit mier zwart (groot)",
      "url": "https://github.com/SamClercky/forme-src/blob/master/tshirtWit_donker.png?raw=true",
      "description": "Wit t-shirt met een exclusieve zwarte mier en onze bedrijfsnaam in het Arabisch.",
      "stars": 0,
      "stared": false,
      "highlighted": false,
      "price": 0
    },
    {
      "label": "T-shirt wit mier rood (groot)",
      "url": "https://github.com/SamClercky/forme-src/blob/master/tshirtWit_finish.png?raw=true",
      "description": "Rood t-shirt met een exclusieve rode mier en onze bedrijfsnaam in het Arabisch.",
      "stars": 0,
      "stared": false,
      "highlighted": false,
      "price": 0
    },
    {
      "label": "T-shirt wit mier rood (klein)",
      "url": "https://github.com/SamClercky/forme-src/blob/master/tshirtWit_finish_klein.png?raw=true",
      "description": "Sober wit t-shirt voor sportevenmenten.",
      "stars": 0,
      "stared": false,
      "highlighted": true,
      "price": 0
    },
    {
      "label": "T-shirt wit lopende mieren",
      "url": "https://github.com/SamClercky/forme-src/blob/master/tshirtWit_finish_v6.png?raw=true",
      "description": "Deluxe wit t-shirt met lopende mieren op borst en rug.",
      "stars": 0,
      "stared": false,
      "highlighted": true,
      "price": 0
    }
  ]
}
